cipred/__init__.py
cipred/lu2019.py
cipred-0.2b0.dist-info/LICENSE
cipred-0.2b0.dist-info/METADATA
cipred-0.2b0.dist-info/WHEEL
cipred-0.2b0.dist-info/top_level.txt
cipred-0.2b0.dist-info/RECORD
