Metadata-Version: 2.1
Name: cipred
Version: 0.2b0
Summary: Non-parametric error prediction with random forest model.
Home-page: https://github.com/j-m-l-e-u/cipred_pkg
Author: Jean-Marie Lepioufle
Author-email: Jean-Marie Lepioufle <jm@jeanmarie.eu>
License: MIT + Copyright Jean-Marie Lepioufle
Project-URL: Homepage, https://github.com/j-m-l-e-u/cipred_pkg
Classifier: Programming Language :: Python :: 3
Requires-Python: >=3.8
License-File: LICENSE
Requires-Dist: polars (~=0.16.9)
Requires-Dist: numpy (~=1.22.4)
Requires-Dist: scikit-learn (~=1.2.1)
Provides-Extra: example
Requires-Dist: ipython ; extra == 'example'
Requires-Dist: jupyter ; extra == 'example'
Requires-Dist: os ; extra == 'example'
Requires-Dist: matplotlib ; extra == 'example'
Requires-Dist: pandas ; extra == 'example'
Requires-Dist: pyarrow ; extra == 'example'
Provides-Extra: examples
Requires-Dist: ipython ; extra == 'examples'
Requires-Dist: jupyter ; extra == 'examples'
Requires-Dist: os ; extra == 'examples'
Requires-Dist: matplotlib ; extra == 'examples'
Requires-Dist: pandas ; extra == 'examples'
Requires-Dist: pyarrow ; extra == 'examples'
